Workbook

Sheet Resumen
B2: FitLoyalty — Seguimiento de requisitos
B3: Estado de implementación verificado contra el código el 2026-10-16 (main @ 54b19fa). Todas las cifras son fórmulas sobre las hojas RF y RNF.
B5: Tipo | C5: Requisitos | D5: Implementados | E5: Parciales | F5: Pendientes | G5: Avance | H5: Meta | I5: Puntos que faltan | J5: Estado | K5: Cantidad
B6: Funcionales | C6: =COUNTA(RF!$A$2:$A$100) -> 22 | D6: =COUNTIF(RF!$C$2:$C$100,"Implementado") -> 10 | E6: =COUNTIF(RF!$C$2:$C$100,"Parcial") -> 8 | F6: =COUNTIF(RF!$C$2:$C$100,"Pendiente") -> 4 | G6: =IF(C6=0,0,SUM(RF!$F$2:$F$100)/C6) -> 0.63636364 | H6: =Resumen!$C$40 -> 0.8 | I6: =MAX(0,H6*C6-G6*C6) -> 3.6 | J6: Implementado | K6: =D8 -> 16
B7: No funcionales | C7: =COUNTA(RNF!$A$2:$A$100) -> 15 | D7: =COUNTIF(RNF!$C$2:$C$100,"Implementado") -> 6 | E7: =COUNTIF(RNF!$C$2:$C$100,"Parcial") -> 6 | F7: =COUNTIF(RNF!$C$2:$C$100,"Pendiente") -> 3 | G7: =IF(C7=0,0,SUM(RNF!$F$2:$F$100)/C7) -> 0.6 | H7: =Resumen!$C$40 -> 0.8 | I7: =MAX(0,H7*C7-G7*C7) -> 3 | J7: Parcial | K7: =E8 -> 14
B8: Total | C8: =C6+C7 -> 37 | D8: =D6+D7 -> 16 | E8: =E6+E7 -> 14 | F8: =F6+F7 -> 7 | G8: =IF(C8=0,0,(SUM(RF!$F$2:$F$100)+SUM(RNF!$F$2:$F$100))/C8) -> 0.62162162 | H8: =Resumen!$C$40 -> 0.8 | I8: =MAX(0,H8*C8-G8*C8) -> 6.6 | J8: Pendiente | K8: =F8 -> 7
B10: Escala editable en B36:C38: Implementado = 1, Parcial = 0,5, Pendiente = 0. Cada estado se respalda con la evidencia de las hojas RF, RNF y Evidencias (archivo:línea).
B29: Solo alcance original del documento (RQF-01..12, RQNF-01..08)
B30: Tipo | C30: Requisitos | D30: Implementados | E30: Parciales | F30: Pendientes | G30: Avance
B31: Funcionales | C31: =COUNTIFS(RF!$A$2:$A$100,"RQ*",RF!$G$2:$G$100,"Original") -> 12 | D31: =COUNTIFS(RF!$C$2:$C$100,"Implementado",RF!$G$2:$G$100,"Original") -> 3 | E31: =COUNTIFS(RF!$C$2:$C$100,"Parcial",RF!$G$2:$G$100,"Original") -> 6 | F31: =COUNTIFS(RF!$C$2:$C$100,"Pendiente",RF!$G$2:$G$100,"Original") -> 3 | G31: =IF(C31=0,0,SUMIFS(RF!$F$2:$F$100,RF!$G$2:$G$100,"Original")/C31) -> 0.5
B32: No funcionales | C32: =COUNTIFS(RNF!$A$2:$A$100,"RQ*",RNF!$G$2:$G$100,"Original") -> 8 | D32: =COUNTIFS(RNF!$C$2:$C$100,"Implementado",RNF!$G$2:$G$100,"Original") -> 2 | E32: =COUNTIFS(RNF!$C$2:$C$100,"Parcial",RNF!$G$2:$G$100,"Original") -> 4 | F32: =COUNTIFS(RNF!$C$2:$C$100,"Pendiente",RNF!$G$2:$G$100,"Original") -> 2 | G32: =IF(C32=0,0,SUMIFS(RNF!$F$2:$F$100,RNF!$G$2:$G$100,"Original")/C32) -> 0.5
B33: Total | C33: =C31+C32 -> 20 | D33: =D31+D32 -> 5 | E33: =E31+E32 -> 10 | F33: =F31+F32 -> 5 | G33: =IF(C33=0,0,(SUMIFS(RF!$F$2:$F$100,RF!$G$2:$G$100,"Original")+SUMIFS(RNF!$F$2:$F$100,RNF!$G$2:$G$100,"Original"))/C33) -> 0.5
B35: Escala (editable)
B36: Implementado | C36: 1 | D36: Criterio acordado con Luis el 2026-10-16: Parcial = lo principal funciona pero falta alguna parte.
B37: Parcial | C37: 0.5
B38: Pendiente | C38: 0
B40: Meta de avance (editable) | C40: 0.8 | D40: Meta del 80 % pedida por Luis para la entrega.

Sheet RF
A1: Código | B1: Módulo / Categoría | C1: Estado | D1: Evidencia en el proyecto | E1: Observaciones / trabajo pendiente | F1: Puntaje | G1: Origen | H1: HU relacionadas | I1: Ref. evidencias | J1: Descripción del requisito
A2: RQF-01 | B2: Gestión de Usuarios | C2: Parcial | D2: Crear (por invitación), listar personal y revocar invitaciones: staff.js:109, :198, :227, :329; aceptar la invitación crea la cuenta: staff.js:384. Roles diferenciados: authorize('admin') en staff.js:112 y miembros.js:667 frente a authorize('admin', 'receptionist') en checkin.js:57. | E2: Editar y eliminar o desactivar cuentas de personal existentes: no hay PUT/DELETE en /api/admin/staff ni acciones en StaffPage.jsx. | F2: =IFERROR(INDEX(Resumen!$C$36:$C$38,MATCH(C2,Resumen!$B$36:$B$38,0)),0) -> 0.5 | G2: Original | H2: HU-01, HU-02, HU-03, HU-04, HU-53 | I2: EV-01, EV-02 | J2: El sistema debe permitir crear, editar, eliminar y consultar cuentas del personal (staff), asignando roles de Administrador o Recepcionista con permisos diferenciados.
A3: RQF-02 | B3: Gestión de Usuarios | C3: Parcial | D3: POST /api/auth/login compara con bcrypt y emite JWT (auth.js:200, :231); cierre manual (auth.js:295, AuthContext.jsx:95); límite de 5 intentos por minuto (index.js:63, :79). | E3: Cierre automático por inactividad (no existe en frontend ni backend). Hallazgo: el JWT del personal no expira, generarToken no aplica JWT_EXPIRES_IN (auth-helpers.js:102-113). | F3: =IFERROR(INDEX(Resumen!$C$36:$C$38,MATCH(C3,Resumen!$B$36:$B$38,0)),0) -> 0.5 | G3: Original | H3: HU-05, HU-06 | I3: EV-03, EV-04 | J3: El sistema debe autenticar al personal mediante usuario y contraseña, gestionando sesiones seguras con cierre automático por inactividad.
A4: RQF-03 | B4: Gestión de Miembros | C4: Implementado | D4: POST /api/admin/miembros rechaza documento o correo duplicados (miembros.js:357-369) y genera un código QR único (:371-379); editar con PUT (:607); desactivar con activo = FALSE (:664-675); pantalla MiembrosPage.jsx:627, :919, :442. | E4: Observación: al editar no se vuelven a validar duplicados de documento o correo (criterio 2 de HU-09). | F4: =IFERROR(INDEX(Resumen!$C$36:$C$38,MATCH(C4,Resumen!$B$36:$B$38,0)),0) -> 1 | G4: Original | H4: HU-07, HU-08, HU-09, HU-10, HU-65 | I4: EV-05, EV-06 | J4: El sistema debe permitir registrar, editar y desactivar perfiles de miembros con datos personales, de contacto e identificador de hardware (código QR o de barras), validando que no existan duplicados por documento o correo.
A5: RQF-04 | B5: Gestión de Miembros | C5: Parcial | D5: Cálculo automático de fecha_fin según el plan (miembros.js:185, :382); estado vencido / por vencer contra la fecha actual (miembros.js:276-284); renovación del plan (miembros.js:754). | E5: Estado Congelada: la tabla congelacion_membresia existe (migración 002:217) pero ninguna ruta ni pantalla la usa. | F5: =IFERROR(INDEX(Resumen!$C$36:$C$38,MATCH(C5,Resumen!$B$36:$B$38,0)),0) -> 0.5 | G5: Original | H5: HU-11, HU-12, HU-13, HU-35..HU-40 | I5: EV-07, EV-08 | J5: El sistema debe controlar el estado de la membresía de cada miembro (Activa, Vencida, Congelada) y calcular automáticamente la fecha de vencimiento a partir del tipo de membresía y fecha de inicio registrados.
A6: RQF-05 | B6: Check-in y Asistencia | C6: Implementado | D6: Campo con autoFocus que recibe la lectura del lector HID tipo teclado y envía con Enter (CheckinPage.jsx:221-223, :329-331); lectura por cámara (CheckinPage.jsx:66); POST /api/admin/checkin inserta el ingreso (checkin.js:54, :167-172); fecha_hora DEFAULT CURRENT_TIMESTAMP (migración 002:100). | E6: — | F6: =IFERROR(INDEX(Resumen!$C$36:$C$38,MATCH(C6,Resumen!$B$36:$B$38,0)),0) -> 1 | G6: Original | H6: HU-14, HU-32, HU-33, HU-34 | I6: EV-09, EV-10 | J6: El sistema debe registrar en tiempo real la entrada de un miembro mediante la lectura pasiva de su código QR o de barras desde un dispositivo HID, almacenando la marca de tiempo exacta del acceso.
A7: RQF-06 | B7: Check-in y Asistencia | C7: Parcial | D7: Valida el último plan y responde VENCIDO sin registrar el ingreso (checkin.js:116-136); la pantalla muestra «Acceso denegado» (CheckinPage.jsx:133-143). | E7: Notificar al administrador del intento bloqueado: el intento no se guarda y la campana (notificaciones.js:96-108) solo lista membresías vencidas, no accesos denegados. | F7: =IFERROR(INDEX(Resumen!$C$36:$C$38,MATCH(C7,Resumen!$B$36:$B$38,0)),0) -> 0.5 | G7: Original | H7: HU-15 | I7: EV-11 | J7: El sistema debe validar el estado de la membresía en el momento del check-in, bloquear el acceso si está vencida y notificar al administrador de forma inmediata.
A8: RQF-07 | B8: Dashboard | C8: Parcial | D8: GET /api/admin/dashboard: miembros activos (dashboard.js:123, :146), entradas de hoy (:128) y próximos vencimientos a 30 días (:204); listado en DashboardPage.jsx:446-473. | E8: Gráfica de horas pico (la gráfica agrupa por día de la semana, dashboard.js:189) y actualización automática (el panel se carga una sola vez, DashboardPage.jsx:165-179). | F8: =IFERROR(INDEX(Resumen!$C$36:$C$38,MATCH(C8,Resumen!$B$36:$B$38,0)),0) -> 0.5 | G8: Original | H8: HU-16, HU-34, HU-41, HU-42, HU-43 | I8: EV-12 | J8: El sistema debe mostrar en tiempo real métricas clave del día: total de entradas, miembros activos, gráficas de horas pico y listado de membresías próximas a vencer.
A9: RQF-08 | B9: Alertas de Abandono | C9: Parcial | D9: Lista de miembros sin ingresar en N días calculada al consultar: campana de avisos (notificaciones.js:125-137; umbral del gimnasio, 15 por defecto, :38 y :66), dashboard (dashboard.js:161, :182) y filtro «En riesgo» de miembros (miembros.js:263, MiembrosPage.jsx:939). | E9: Ejecución diaria del motor (el scheduler solo programa vencimientos, scheduler.js:46), los dos niveles Amarilla / Roja, registro en alerta_abandono (tabla sin uso) y pantalla para configurar el umbral (el dashboard usa 15 días fijos). | F9: =IFERROR(INDEX(Resumen!$C$36:$C$38,MATCH(C9,Resumen!$B$36:$B$38,0)),0) -> 0.5 | G9: Original | H9: HU-17, HU-18, HU-44, HU-64 | I9: EV-13, EV-14 | J9: El sistema debe ejecutar diariamente un motor de detección que clasifique a los miembros según umbrales de inactividad configurables (Alerta Amarilla ≥ 7 días, Alerta Roja ≥ 15 días) y los liste en el panel del administrador.
A10: RQF-09 | B10: Alertas de Abandono | C10: Implementado | D10: Botón de WhatsApp con el mensaje armado para miembros en riesgo (MenuNotificaciones.jsx:86-90, MiembrosPage.jsx:796-802); POST /api/admin/notificaciones/enviado guarda canal, estado ENVIADO y fecha en envio_mensaje (notificaciones.js:188-224). | E10: Observación: solo WhatsApp por enlace wa.me; el estado no confirma la entrega y el correo no se usa para retención. | F10: =IFERROR(INDEX(Resumen!$C$36:$C$38,MATCH(C10,Resumen!$B$36:$B$38,0)),0) -> 1 | G10: Original | H10: HU-19, HU-20, HU-52 | I10: EV-15 | J10: El sistema debe permitir al administrador enviar mensajes de retención a miembros inactivos a través del canal de comunicación configurado (correo o WhatsApp), registrando la fecha y estado de cada envío.
A11: RQF-10 | B11: Campañas | C11: Pendiente | D11: Solo existen las tablas campana, campana_destinatario y plantilla_mensaje (migración 002:171-202); ninguna ruta ni pantalla las usa. | E11: Todo el módulo: rutas de API, programación de envíos, segmentos y pantalla. | F11: =IFERROR(INDEX(Resumen!$C$36:$C$38,MATCH(C11,Resumen!$B$36:$B$38,0)),0) -> 0 | G11: Original | H11: HU-21..HU-24, HU-45, HU-46 | I11: EV-16 | J11: El sistema debe permitir crear, programar y ejecutar campañas de mensajes dirigidas a segmentos de miembros definidos (inactivos, nuevos, próximos a vencer), con soporte para plantillas de mensaje reutilizables.
A12: RQF-11 | B12: Gamificación | C12: Pendiente | D12: La app del miembro lee hitos y su estado (cliente.js:340-381, gamificacion_screen.dart), pero ningún archivo calcula rachas ni escribe hito_miembro; los datos que existen vienen del script ConsultasDB/Poblar_Tablas.sql:384-419. | E12: Cálculo de rachas en cada check-in, otorgar hitos, mensaje en la pantalla de check-in y configuración de hitos por el administrador. | F12: =IFERROR(INDEX(Resumen!$C$36:$C$38,MATCH(C12,Resumen!$B$36:$B$38,0)),0) -> 0 | G12: Original | H12: HU-25, HU-26, HU-27, HU-47, HU-48 | I12: EV-17 | J12: El sistema debe calcular automáticamente las rachas de asistencia de cada miembro y mostrar un mensaje motivacional en la pantalla del check-in al alcanzar un hito configurado por el administrador.
A13: RQF-12 | B13: Gamificación | C13: Pendiente | D13: La app lista los retos activos con el progreso guardado (cliente.js:392-418), pero no hay ruta ni pantalla para crear retos, el check-in no actualiza reto_miembro y no hay aviso al completar; los retos existentes vienen de ConsultasDB/Poblar_Tablas.sql:456-490. | E13: CRUD de retos para el administrador, actualización del progreso en cada check-in y notificación al completar. | F13: =IFERROR(INDEX(Resumen!$C$36:$C$38,MATCH(C13,Resumen!$B$36:$B$38,0)),0) -> 0 | G13: Original | H13: HU-28..HU-31, HU-49, HU-50 | I13: EV-18 | J13: El sistema debe permitir al administrador crear retos de asistencia con meta, duración, segmento elegible y recompensa; registrar el progreso de cada miembro inscrito y notificar al administrador y al miembro al completar el reto.
... A23: RQF-22 | B23: Cumplimiento | C23: Pendiente | D23: DELETE /api/auth/account (auth.js:480-561) borra en una transacción con safe(), que solo ignora el código 42P01 y no usa SAVEPOINT (auth.js:496-502). En PostgreSQL cualquier error, incluso el ignorado, aborta la transacción: con las migraciones falla en DELETE FROM auditoria (ninguna migración crea esa tabla) y con el esquema de ConsultasDB el INSERT en auditoria viola la llave foránea hacia el usuario borrado. En los dos casos el gimnasio queda intacto y la API responde 500. Probado en PostgreSQL 18 en el informe del verificador (70dd13c, sección 11.2.1). | E23: Un SAVEPOINT por cada safe() (o quitar las tablas que no existen) y no insertar en auditoria filas que apunten al usuario y al gimnasio que se borran. Si se corrige y se prueba, puede volver a Implementado. El PR #4 y mi versión anterior lo daban por Implementado leyendo solo el código. | F23: =IFERROR(INDEX(Resumen!$C$36:$C$38,MATCH(C23,Resumen!$B$36:$B$38,0)),0) -> 0 | G23: Nuevo | H23: HU-63 | I23: EV-32, EV-33 | J23: El sistema debe permitir al propietario eliminar su cuenta y los datos asociados del gimnasio.

Sheet RNF
A1: Código | B1: Módulo / Categoría | C1: Estado | D1: Evidencia en el proyecto | E1: Observaciones / trabajo pendiente | F1: Puntaje | G1: Origen | H1: HU relacionadas | I1: Ref. evidencias | J1: Descripción del requisito
A2: RQNF-01 | B2: Rendimiento | C2: Pendiente | D2: No hay medición registrada. | E2: Primero corregir la búsqueda del QR (paso 11 de «Trabajo pendiente»): si el QR no coincide directo, checkin.js:83-101 descifra en memoria los QR de todos los miembros del gimnasio. Después, medir el check-in con un volumen realista (unos 200 miembros) y registrar el tiempo de respuesta de POST /api/admin/checkin. | F2: =IFERROR(INDEX(Resumen!$C$36:$C$38,MATCH(C2,Resumen!$B$36:$B$38,0)),0) -> 0 | G2: Original | H2: — | I2: EV-34 | J2: El sistema debe procesar y confirmar cada registro de check-in en un tiempo máximo de 2 segundos desde la lectura del dispositivo HID.
A3: RQNF-02 | B3: Disponibilidad | C3: Pendiente | D3: Existen /api/healthz y /api/health (index.js:101, :103), pero no hay monitoreo ni reporte de disponibilidad. | E3: Monitor externo sobre /api/healthz con reporte del período; el plan gratuito de Render suspende el servicio por inactividad (scheduler.js:9-10). | F3: =IFERROR(INDEX(Resumen!$C$36:$C$38,MATCH(C3,Resumen!$B$36:$B$38,0)),0) -> 0 | G3: Original | H3: — | I3: EV-35 | J3: El sistema debe garantizar una disponibilidad mínima del 99% durante el horario operativo del gimnasio (lunes a domingo, 5:00 a.m. – 10:00 p.m.).
A4: RQNF-03 | B4: Seguridad | C4: Implementado | D4: bcrypt.hash / compare en registro, login, restablecimiento e invitación (auth.js:145, :231, :447; staff.js:431) y para miembros (miembros.js:388, :625; cliente.js:88); API de producción por HTTPS (frontend/src/api.js:26) y frontend en Vercel con HTTPS. | E4: Observación: la clave de cifrado del QR tiene un valor por defecto en el código (miembros.js:36, checkin.js:19). | F4: =IFERROR(INDEX(Resumen!$C$36:$C$38,MATCH(C4,Resumen!$B$36:$B$38,0)),0) -> 1 | G4: Original | H4: — | I4: EV-36 | J4: El sistema debe almacenar las contraseñas del personal utilizando cifrado hash (bcrypt o equivalente) y todas las comunicaciones deben realizarse bajo protocolo HTTPS.
A5: RQNF-04 | B5: Usabilidad | C5: Parcial | D5: Registro manual en 2 interacciones: escribir el documento y pulsar «Registrar» (CheckinPage.jsx:333, :341-347); el código QR se envía con Enter (CheckinPage.jsx:221-223). | E5: Prueba de usabilidad documentada con personal sin formación técnica (p. ej. 3 personas, conteo de interacciones y tiempo). | F5: =IFERROR(INDEX(Resumen!$C$36:$C$38,MATCH(C5,Resumen!$B$36:$B$38,0)),0) -> 0.5 | G5: Original | H5: HU-32 | I5: EV-37 | J5: La interfaz del módulo de check-in debe ser operable por personal sin formación técnica, con un flujo de no más de 2 interacciones para registrar una entrada de forma manual.
A6: RQNF-05 | B6: Escalabilidad | C6: Parcial | D6: Cada gimnasio nuevo se crea por registro, sin tocar código (auth.js:100, :134); casi todas las consultas filtran por el id_gimnasio del token (p. ej. miembros.js:358, checkin.js:76, dashboard.js:123, notificaciones.js:199; admin-contrato.js:92). | E6: GET /api/vista/miembros-activos no filtra por gimnasio (vista.js:27-42) y rompe el aislamiento entre gimnasios. No hay prueba de carga que respalde «sin degradación del rendimiento». | F6: =IFERROR(INDEX(Resumen!$C$36:$C$38,MATCH(C6,Resumen!$B$36:$B$38,0)),0) -> 0.5 | G6: Original | H6: HU-56 | I6: EV-38, EV-39 | J6: La arquitectura SaaS debe soportar el registro de múltiples gimnasios (multitenancy) sin degradación del rendimiento, permitiendo incorporar nuevos establecimientos sin modificaciones en el código base.
A7: RQNF-06 | B7: Compatibilidad | C7: Parcial | D7: Aplicación web React / Vite servida por Vercel que solo requiere navegador (frontend/package.json, vercel.json); QA responsive a 375 px (Evidencias_Sustentacion/QA_Responsive_375px.md). | E7: Prueba documentada en Chrome, Firefox y Edge (lista de verificación de las pantallas principales con capturas). | F7: =IFERROR(INDEX(Resumen!$C$36:$C$38,MATCH(C7,Resumen!$B$36:$B$38,0)),0) -> 0.5 | G7: Original | H7: — | I7: EV-40 | J7: El sistema debe funcionar correctamente en los navegadores Chrome, Firefox y Edge en sus dos últimas versiones mayores, sin requerir instalación de software adicional en el cliente.
A8: RQNF-07 | B8: Mantenibilidad | C8: Parcial | D8: Capas en backend/src (routes, lib, middleware, jobs, db) y diagrama de arquitectura en el documento (sección 8). Cobertura medida el 2026-10-16: 0 % en routes/checkin.js y routes/notificaciones.js, 1,48 % de líneas en todo el backend; 23 pruebas, 2 fallan. | E8: Script «test» en backend/package.json, pruebas de check-in y alertas hasta ≥ 70 % y corregir las 2 pruebas que fallan. | F8: =IFERROR(INDEX(Resumen!$C$36:$C$38,MATCH(C8,Resumen!$B$36:$B$38,0)),0) -> 0.5 | G8: Original | H8: — | I8: EV-41, EV-42 | J8: El código fuente debe seguir una arquitectura en capas documentada, con una cobertura mínima de pruebas unitarias del 70% sobre los módulos de check-in y alertas de abandono.
A9: RQNF-08 | B9: Portabilidad | C9: Implementado | D9: backend/Dockerfile (node:24-alpine, multietapa), frontend/Dockerfile + nginx.conf y docker-compose.yml; despliegue en la nube en Render y Vercel (render.yaml, vercel.json). | E9: Observación: no se verificó la construcción de la imagen (Docker Desktop apagado) y Render usa el entorno Node nativo, no el contenedor. Sugerencia: agregar docker build al CI. | F9: =IFERROR(INDEX(Resumen!$C$36:$C$38,MATCH(C9,Resumen!$B$36:$B$38,0)),0) -> 1 | G9: Original | H9: — | I9: EV-43 | J9: El sistema debe poder desplegarse en servicios de nube (AWS, Railway, Render o equivalentes) mediante contenedores Docker, sin dependencia de infraestructura física local.
A10: RQNF-09 | B10: Seguridad | C10: Parcial | D10: express-rate-limit: inicio de sesión 5 por minuto, recuperación de contraseña 3 por minuto y login de la app 10 por minuto (index.js:63-77, :79-80, :94); trust proxy para tomar la IP real detrás de Render (index.js:43). | E10: verify-reset-code (auth.js:360) y reset-password (auth.js:399) no tienen límite: el código de 6 dígitos se puede probar sin límite durante sus 15 minutos de vida. | F10: =IFERROR(INDEX(Resumen!$C$36:$C$38,MATCH(C10,Resumen!$B$36:$B$38,0)),0) -> 0.5 | G10: Nuevo | H10: — | I10: EV-44 | J10: El sistema debe limitar la tasa de intentos en los endpoints de inicio de sesión, recuperación de contraseña e inicio de sesión de la app del miembro.
A11: RQNF-10 | B11: Mantenibilidad | C11: Parcial | D11: applyMigrations lee backend/migrations en orden, aplica solo las pendientes y las registra en schema_migrations (migrate.js:15-56); se ejecuta al arrancar (index.js:128-132). Migraciones 002 a 008 en backend/migrations. | E11: Una base creada solo con backend/migrations no tiene vista_miembros_activos ni auditoria, y reto tiene meta en lugar de meta_asistencias (002_esquema_inicial.sql:278-290); el esquema de producción salió de ConsultasDB/ y de cambios manuales. Probado en el informe del verificador (70dd13c, sección 11.2.1). Además hay prefijos repetidos (004 y 005) y backend/src/db/migrations/001_invitacion_staff.sql no se aplica. | F11: =IFERROR(INDEX(Resumen!$C$36:$C$38,MATCH(C11,Resumen!$B$36:$B$38,0)),0) -> 0.5 | G11: Nuevo | H11: — | I11: EV-45 | J11: El esquema de la base de datos debe evolucionar mediante migraciones versionadas aplicadas automáticamente al iniciar el servicio.
A12: RQNF-11 | B12: Mantenibilidad | C12: Implementado | D12: .github/workflows/ci.yml corre en pull_request y en push a main (:3-6): el job rama valida el nombre de la rama en cada PR (:13-26), backend npm ci + node --check (:42-44) y frontend npm ci + build (:58-59); ejecución exitosa en main 8acab31 (pestaña Actions). | E12: Observación: el CI todavía no corre pruebas ni mide cobertura. | F12: =IFERROR(INDEX(Resumen!$C$36:$C$38,MATCH(C12,Resumen!$B$36:$B$38,0)),0) -> 1 | G12: Nuevo | H12: — | I12: EV-46 | J12: El repositorio debe ejecutar integración continua en cada pull request y en cada cambio de la rama principal: nombre de la rama, instalación limpia de dependencias, comprobación de sintaxis del backend y compilación del frontend.
A13: RQNF-12 | B13: Cumplimiento | C13: Implementado | D13: Rutas públicas /legal/terminos, /legal/privacidad y /legal/datos (App.jsx:43-45) con TerminosPage.jsx, PrivacidadPage.jsx y PoliticaDatosPage.jsx. | E13: — | F13: =IFERROR(INDEX(Resumen!$C$36:$C$38,MATCH(C13,Resumen!$B$36:$B$38,0)),0) -> 1 | G13: Nuevo | H13: — | I13: EV-47 | J13: El sistema debe publicar los términos de uso, la política de privacidad y la política de tratamiento de datos personales.
... A16: RQNF-15 | B16: Seguridad | C16: Pendiente | D16: La configuración de CORS lee FRONTEND_URL (index.js:45-48), pero el callback devuelve permitido también para orígenes que no están en la lista (index.js:54), con credentials: true. | E16: Rechazar los orígenes que no estén en FRONTEND_URL (cambiar index.js:54). El PR #4 lo marcaba Implementado. | F16: =IFERROR(INDEX(Resumen!$C$36:$C$38,MATCH(C16,Resumen!$B$36:$B$38,0)),0) -> 0 | G16: Nuevo | H16: — | I16: EV-50 | J16: El sistema debe restringir las solicitudes entre orígenes (CORS) a los dominios configurados.

Sheet Trabajo pendiente
A1: Código | B1: Estado | C1: Pendiente | D1: Acción propuesta | E1: Responsable | F1: Esfuerzo | G1: Puntos que suma | H1: Avance global acumulado
A2: RQNF-15 | B2: =IFERROR(INDEX(RF!$C$2:$C$100,MATCH($A2,RF!$A$2:$A$100,0)),INDEX(RNF!$C$2:$C$100,MATCH($A2,RNF!$A$2:$A$100,0))) -> Pendiente | C2: Rechazar los orígenes que no estén en FRONTEND_URL (cambiar index.js:54). El PR #4 lo marcaba Implementado. | D2: Rechazar en CORS los orígenes que no estén en FRONTEND_URL (index.js:54) | E2: Santiago | F2: Bajo | G2: =1-IFERROR(INDEX(RF!$F$2:$F$100,MATCH($A2,RF!$A$2:$A$100,0)),INDEX(RNF!$F$2:$F$100,MATCH($A2,RNF!$A$2:$A$100,0))) -> 1 | H2: =(Resumen!$G$8*Resumen!$C$8+SUM($G$2:G2))/Resumen!$C$8 -> 0.64864865
A3: RQF-22 | B3: =IFERROR(INDEX(RF!$C$2:$C$100,MATCH($A3,RF!$A$2:$A$100,0)),INDEX(RNF!$C$2:$C$100,MATCH($A3,RNF!$A$2:$A$100,0))) -> Pendiente | C3: Un SAVEPOINT por cada safe() (o quitar las tablas que no existen) y no insertar en auditoria filas que apunten al usuario y al gimnasio que se borran. Si se corrige y se prueba, puede volver a Implementado. El PR #4 y mi versión anterior lo daban por Implementado leyendo solo el código. | D3: Un SAVEPOINT por cada safe() y no insertar en auditoria lo que se borra; probar la eliminación | E3: Santiago | F3: Bajo | G3: =1-IFERROR(INDEX(RF!$F$2:$F$100,MATCH($A3,RF!$A$2:$A$100,0)),INDEX(RNF!$F$2:$F$100,MATCH($A3,RNF!$A$2:$A$100,0))) -> 1 | H3: =(Resumen!$G$8*Resumen!$C$8+SUM($G$2:G3))/Resumen!$C$8 -> 0.67567568
A4: RQF-13 | B4: =IFERROR(INDEX(RF!$C$2:$C$100,MATCH($A4,RF!$A$2:$A$100,0)),INDEX(RNF!$C$2:$C$100,MATCH($A4,RNF!$A$2:$A$100,0))) -> Parcial | C4: Con el cliente listo, un envío que falla queda registrado como exitoso: sendWhatsAppText se traga el error (whatsapp.js:244-246) y el catch de admin-contrato.js:132-138 nunca se ejecuta. Arreglo: relanzar el error en sendWhatsAppText. | D4: Relanzar el error en sendWhatsAppText para que un envío fallido no quede como exitoso | E4: Santiago | F4: Bajo | G4: =1-IFERROR(INDEX(RF!$F$2:$F$100,MATCH($A4,RF!$A$2:$A$100,0)),INDEX(RNF!$F$2:$F$100,MATCH($A4,RNF!$A$2:$A$100,0))) -> 0.5 | H4: =(Resumen!$G$8*Resumen!$C$8+SUM($G$2:G4))/Resumen!$C$8 -> 0.68918919
A5: RQF-14 | B5: =IFERROR(INDEX(RF!$C$2:$C$100,MATCH($A5,RF!$A$2:$A$100,0)),INDEX(RNF!$C$2:$C$100,MATCH($A5,RNF!$A$2:$A$100,0))) -> Parcial | C5: Si WhatsApp no está listo, sendWhatsAppText vuelve sin error (whatsapp.js:228-231) y el job marca el aviso como enviado (expiracion.js:206-207), así que nunca lo reintenta; en Render no hay Chrome (whatsapp.js:7-25). Los días de anticipación (gimnasio.dias_aviso_vencimiento) solo se cambian en la base de datos: PUT /admin/config no los acepta (config.js:20-30). | D5: No marcar el aviso como enviado si WhatsApp no está listo (reintentar) y llevar los días a Configuración | E5: Santiago | F5: Bajo | G5: =1-IFERROR(INDEX(RF!$F$2:$F$100,MATCH($A5,RF!$A$2:$A$100,0)),INDEX(RNF!$F$2:$F$100,MATCH($A5,RNF!$A$2:$A$100,0))) -> 0.5 | H5: =(Resumen!$G$8*Resumen!$C$8+SUM($G$2:G5))/Resumen!$C$8 -> 0.7027027
A6: RQNF-09 | B6: =IFERROR(INDEX(RF!$C$2:$C$100,MATCH($A6,RF!$A$2:$A$100,0)),INDEX(RNF!$C$2:$C$100,MATCH($A6,RNF!$A$2:$A$100,0))) -> Parcial | C6: verify-reset-code (auth.js:360) y reset-password (auth.js:399) no tienen límite: el código de 6 dígitos se puede probar sin límite durante sus 15 minutos de vida. | D6: Límite de intentos en verify-reset-code y reset-password | E6: Santiago | F6: Bajo | G6: =1-IFERROR(INDEX(RF!$F$2:$F$100,MATCH($A6,RF!$A$2:$A$100,0)),INDEX(RNF!$F$2:$F$100,MATCH($A6,RNF!$A$2:$A$100,0))) -> 0.5 | H6: =(Resumen!$G$8*Resumen!$C$8+SUM($G$2:G6))/Resumen!$C$8 -> 0.71621622
A7: RQNF-04 | B7: =IFERROR(INDEX(RF!$C$2:$C$100,MATCH($A7,RF!$A$2:$A$100,0)),INDEX(RNF!$C$2:$C$100,MATCH($A7,RNF!$A$2:$A$100,0))) -> Parcial | C7: Prueba de usabilidad documentada con personal sin formación técnica (p. ej. 3 personas, conteo de interacciones y tiempo). | D7: Prueba de usabilidad del check-in manual con 3 personas sin formación técnica | E7: Luis | F7: Bajo | G7: =1-IFERROR(INDEX(RF!$F$2:$F$100,MATCH($A7,RF!$A$2:$A$100,0)),INDEX(RNF!$F$2:$F$100,MATCH($A7,RNF!$A$2:$A$100,0))) -> 0.5 | H7: =(Resumen!$G$8*Resumen!$C$8+SUM($G$2:G7))/Resumen!$C$8 -> 0.72972973
A8: RQNF-06 | B8: =IFERROR(INDEX(RF!$C$2:$C$100,MATCH($A8,RF!$A$2:$A$100,0)),INDEX(RNF!$C$2:$C$100,MATCH($A8,RNF!$A$2:$A$100,0))) -> Parcial | C8: Prueba documentada en Chrome, Firefox y Edge (lista de verificación de las pantallas principales con capturas). | D8: Lista de verificación con capturas en Chrome, Firefox y Edge | E8: Luis | F8: Bajo | G8: =1-IFERROR(INDEX(RF!$F$2:$F$100,MATCH($A8,RF!$A$2:$A$100,0)),INDEX(RNF!$F$2:$F$100,MATCH($A8,RNF!$A$2:$A$100,0))) -> 0.5 | H8: =(Resumen!$G$8*Resumen!$C$8+SUM($G$2:G8))/Resumen!$C$8 -> 0.74324324
A9: RQF-02 | B9: =IFERROR(INDEX(RF!$C$2:$C$100,MATCH($A9,RF!$A$2:$A$100,0)),INDEX(RNF!$C$2:$C$100,MATCH($A9,RNF!$A$2:$A$100,0))) -> Parcial | C9: Cierre automático por inactividad (no existe en frontend ni backend). Hallazgo: el JWT del personal no expira, generarToken no aplica JWT_EXPIRES_IN (auth-helpers.js:102-113). | D9: Cierre de sesión por inactividad en el frontend y expiración real del JWT | E9: Santiago | F9: Bajo | G9: =1-IFERROR(INDEX(RF!$F$2:$F$100,MATCH($A9,RF!$A$2:$A$100,0)),INDEX(RNF!$F$2:$F$100,MATCH($A9,RNF!$A$2:$A$100,0))) -> 0.5 | H9: =(Resumen!$G$8*Resumen!$C$8+SUM($G$2:G9))/Resumen!$C$8 -> 0.75675676
A10: RQF-07 | B10: =IFERROR(INDEX(RF!$C$2:$C$100,MATCH($A10,RF!$A$2:$A$100,0)),INDEX(RNF!$C$2:$C$100,MATCH($A10,RNF!$A$2:$A$100,0))) -> Parcial | C10: Gráfica de horas pico (la gráfica agrupa por día de la semana, dashboard.js:189) y actualización automática (el panel se carga una sola vez, DashboardPage.jsx:165-179). | D10: Gráfica de horas pico y refresco automático del dashboard | E10: Santiago | F10: Bajo | G10: =1-IFERROR(INDEX(RF!$F$2:$F$100,MATCH($A10,RF!$A$2:$A$100,0)),INDEX(RNF!$F$2:$F$100,MATCH($A10,RNF!$A$2:$A$100,0))) -> 0.5 | H10: =(Resumen!$G$8*Resumen!$C$8+SUM($G$2:G10))/Resumen!$C$8 -> 0.77027027
A11: RQF-06 | B11: =IFERROR(INDEX(RF!$C$2:$C$100,MATCH($A11,RF!$A$2:$A$100,0)),INDEX(RNF!$C$2:$C$100,MATCH($A11,RNF!$A$2:$A$100,0))) -> Parcial | C11: Notificar al administrador del intento bloqueado: el intento no se guarda y la campana (notificaciones.js:96-108) solo lista membresías vencidas, no accesos denegados. | D11: Registrar el acceso bloqueado y mostrarlo en la campana del administrador | E11: Santiago | F11: Bajo | G11: =1-IFERROR(INDEX(RF!$F$2:$F$100,MATCH($A11,RF!$A$2:$A$100,0)),INDEX(RNF!$F$2:$F$100,MATCH($A11,RNF!$A$2:$A$100,0))) -> 0.5 | H11: =(Resumen!$G$8*Resumen!$C$8+SUM($G$2:G11))/Resumen!$C$8 -> 0.78378378
A12: RQNF-05 | B12: =IFERROR(INDEX(RF!$C$2:$C$100,MATCH($A12,RF!$A$2:$A$100,0)),INDEX(RNF!$C$2:$C$100,MATCH($A12,RNF!$A$2:$A$100,0))) -> Parcial | C12: GET /api/vista/miembros-activos no filtra por gimnasio (vista.js:27-42) y rompe el aislamiento entre gimnasios. No hay prueba de carga que respalde «sin degradación del rendimiento». | D12: Cerrar la fuga de vista.js, exigir rol de personal en /api/asistencia y quitar scryptSync del recorrido del check-in | E12: Santiago | F12: Medio | G12: =1-IFERROR(INDEX(RF!$F$2:$F$100,MATCH($A12,RF!$A$2:$A$100,0)),INDEX(RNF!$F$2:$F$100,MATCH($A12,RNF!$A$2:$A$100,0))) -> 0.5 | H12: =(Resumen!$G$8*Resumen!$C$8+SUM($G$2:G12))/Resumen!$C$8 -> 0.7972973
A13: RQNF-01 | B13: =IFERROR(INDEX(RF!$C$2:$C$100,MATCH($A13,RF!$A$2:$A$100,0)),INDEX(RNF!$C$2:$C$100,MATCH($A13,RNF!$A$2:$A$100,0))) -> Pendiente | C13: Primero corregir la búsqueda del QR (paso 11 de «Trabajo pendiente»): si el QR no coincide directo, checkin.js:83-101 descifra en memoria los QR de todos los miembros del gimnasio. Después, medir el check-in con un volumen realista (unos 200 miembros) y registrar el tiempo de respuesta de POST /api/admin/checkin. | D13: Con la búsqueda del QR ya corregida (paso anterior), medir el check-in con un volumen realista (unos 200 miembros) | E13: Luis o Santiago | F13: Medio | G13: =1-IFERROR(INDEX(RF!$F$2:$F$100,MATCH($A13,RF!$A$2:$A$100,0)),INDEX(RNF!$F$2:$F$100,MATCH($A13,RNF!$A$2:$A$100,0))) -> 1 | H13: =(Resumen!$G$8*Resumen!$C$8+SUM($G$2:G13))/Resumen!$C$8 -> 0.82432432
... A22: RQF-10 | B22: =IFERROR(INDEX(RF!$C$2:$C$100,MATCH($A22,RF!$A$2:$A$100,0)),INDEX(RNF!$C$2:$C$100,MATCH($A22,RNF!$A$2:$A$100,0))) -> Pendiente | C22: Todo el módulo: rutas de API, programación de envíos, segmentos y pantalla. | D22: Módulo de campañas y plantillas | E22: Santiago | F22: Alto | G22: =1-IFERROR(INDEX(RF!$F$2:$F$100,MATCH($A22,RF!$A$2:$A$100,0)),INDEX(RNF!$F$2:$F$100,MATCH($A22,RNF!$A$2:$A$100,0))) -> 1 | H22: =(Resumen!$G$8*Resumen!$C$8+SUM($G$2:G22))/Resumen!$C$8 -> 1
A24: Orden de menor a mayor esfuerzo. «Avance global acumulado» suma los puntos de cada acción, en orden, sobre el avance actual y se pone verde al llegar a la meta. Lo decide Luis; las implementaciones las hace Santiago.

Sheet Evidencias
A1: ID | B1: Requisito | C1: Tipo | D1: Ubicación (archivo:línea, endpoint o enlace) | E1: Qué demuestra | F1: Fecha de verificación | G1: Verificado por
A2: EV-01 | B2: RQF-01 | C2: Código | D2: backend/src/routes/staff.js:109, :198, :227, :329, :384 | E2: Invitar, listar y revocar personal; aceptar la invitación crea la cuenta. | F2: 2026-10-16 | G2: Agente ejecutor (Claude)
A3: EV-02 | B3: RQF-01 | C3: Código | D3: backend/src/routes/staff.js:112; miembros.js:667; checkin.js:57; middleware/auth.js:29 | E3: Permisos distintos para Administrador y Recepcionista. | F3: 2026-10-16 | G3: Agente ejecutor (Claude)
A4: EV-03 | B4: RQF-02 | C4: Código | D4: backend/src/routes/auth.js:200, :231, :295; frontend/src/context/AuthContext.jsx:95 | E4: Login con bcrypt + JWT y cierre de sesión manual. | F4: 2026-10-16 | G4: Agente ejecutor (Claude)
A5: EV-04 | B5: RQF-02 | C5: Código (hallazgo) | D5: backend/src/lib/auth-helpers.js:102-113 | E5: generarToken no aplica JWT_EXPIRES_IN: el token del personal no expira. | F5: 2026-10-16 | G5: Agente ejecutor (Claude)
A6: EV-05 | B6: RQF-03 | C6: Código | D6: backend/src/routes/miembros.js:357-369, :371-379 | E6: Rechazo de documento / correo duplicado y QR único. | F6: 2026-10-16 | G6: Agente ejecutor (Claude)
A7: EV-06 | B7: RQF-03 | C7: Código | D7: backend/src/routes/miembros.js:607, :664-675; frontend/src/pages/MiembrosPage.jsx:627, :919, :442 | E7: Editar y desactivar (soft delete) desde la pantalla de miembros. | F7: 2026-10-16 | G7: Agente ejecutor (Claude)
A8: EV-07 | B8: RQF-04 | C8: Código | D8: backend/src/routes/miembros.js:185, :382, :276-284, :754 | E8: Fecha de vencimiento automática, estado vencido / por vencer y renovación. | F8: 2026-10-16 | G8: Agente ejecutor (Claude)
A9: EV-08 | B9: RQF-04 | C9: Esquema | D9: backend/migrations/002_esquema_inicial.sql:217 | E9: congelacion_membresia existe pero no se usa (falta Congelada). | F9: 2026-10-16 | G9: Agente ejecutor (Claude)
A10: EV-09 | B10: RQF-05 | C10: Código | D10: frontend/src/pages/CheckinPage.jsx:66, :221-223, :329-331 | E10: Lectura HID tipo teclado (autoFocus + Enter) y por cámara. | F10: 2026-10-16 | G10: Agente ejecutor (Claude)
A11: EV-10 | B11: RQF-05 | C11: Código / esquema | D11: backend/src/routes/checkin.js:54, :167-172; backend/migrations/002_esquema_inicial.sql:100 | E11: Inserción del ingreso con marca de tiempo automática. | F11: 2026-10-16 | G11: Agente ejecutor (Claude)
A12: EV-11 | B12: RQF-06 | C12: Código | D12: backend/src/routes/checkin.js:116-136; frontend/src/pages/CheckinPage.jsx:133-143 | E12: Bloqueo de membresía vencida; no hay aviso del intento al administrador. | F12: 2026-10-16 | G12: Agente ejecutor (Claude)
... A51: EV-50 | B51: RQNF-15 | C51: Código (hallazgo) | D51: backend/src/index.js:45-57 | E51: CORS acepta cualquier origen. | F51: 2026-10-16 | G51: Agente ejecutor (Claude)
A53: Rutas relativas a la raíz del repositorio en main @ 54b19fa (el CI de RQNF-11 en 8acab31). No se hicieron pruebas en vivo: la verificación es por lectura de código, pruebas existentes y CI.
